<dict><word>cosavior</word><word>coscet</word><word>coscinodiscaceae</word><word>coscinodiscus</word><word>coscinomancy</word><word>coscoroba</word><word>coseasonal</word><word>coseat</word><word>cosec</word><word>cosecant</word><word>cosech</word><word>cosectarian</word><word>cosectional</word><word>cosegment</word><word>coseism</word><word>coseismal</word><word>coseismic</word><word>cosenator</word><word>cosentiency</word><word>cosentient</word><word>coservant</word><word>cosession</word><word>coset</word><word>cosettler</word><word>cosh</word><word>cosharer</word><word>cosheath</word><word>cosher</word><word>cosherer</word><word>coshering</word><word>coshery</word><word>cosignatory</word><word>cosigner</word><word>cosignitary</word><word>cosily</word><word>cosinage</word><word>cosine</word><word>cosiness</word><word>cosingular</word><word>cosinusoid</word><word>cosmati</word><word>cosmecology</word><word>cosmesis</word><word>cosmetic</word><word>cosmetical</word><word>cosmetically</word><word>cosmetician</word><word>cosmetiste</word><word>cosmetological</word><word>cosmetologist</word><word>cosmetology</word><word>cosmic</word><word>cosmical</word><word>cosmicality</word><word>cosmically</word><word>cosmism</word><word>cosmist</word><word>cosmocracy</word><word>cosmocrat</word><word>cosmocratic</word><word>cosmogenesis</word><word>cosmogenetic</word><word>cosmogenic</word><word>cosmogeny</word><word>cosmogonal</word><word>cosmogoner</word><word>cosmogonic</word><word>cosmogonical</word><word>cosmogonist</word><word>cosmogonize</word><word>cosmogony</word><word>cosmographer</word><word>cosmographic</word><word>cosmographical</word><word>cosmographically</word><word>cosmographist</word><word>cosmography</word><word>cosmolabe</word><word>cosmolatry</word><word>cosmologic</word><word>cosmological</word><word>cosmologically</word><word>cosmologist</word><word>cosmology</word><word>cosmometry</word><word>cosmopathic</word><word>cosmoplastic</word><word>cosmopoietic</word><word>cosmopolicy</word><word>cosmopolis</word><word>cosmopolitan</word><word>cosmopolitanism</word><word>cosmopolitanization</word><word>cosmopolitanize</word><word>cosmopolitanly</word><word>cosmopolite</word><word>cosmopolitic</word><word>cosmopolitical</word><word>cosmopolitics</word><word>cosmopolitism</word><word>cosmorama</word><word>cosmoramic</word><word>cosmorganic</word><word>cosmos</word><word>cosmoscope</word><word>cosmosophy</word><word>cosmosphere</word><word>cosmotellurian</word><word>cosmotheism</word><word>cosmotheist</word><word>cosmotheistic</word><word>cosmothetic</word><word>cosmotron</word><word>cosmozoan</word><word>cosmozoic</word><word>cosmozoism</word><word>cosonant</word><word>cosounding</word><word>cosovereign</word><word>cosovereignty</word><word>cospecies</word><word>cospecific</word><word>cosphered</word><word>cosplendor</word><word>cosplendour</word><word>coss</word><word>cossack</word><word>cossaean</word><word>cossas</word><word>cosse</word><word>cosset</word><word>cossette</word><word>cossid</word><word>cossidae</word><word>cossnent</word><word>cossyrite</word><word>cost</word><word>costa</word><word>costaea</word><word>costal</word><word>costalgia</word><word>costally</word><word>costander</word><word>costanoan</word><word>costar</word><word>costard</word><word>costata</word><word>costate</word><word>costated</word><word>costean</word><word>costeaning</word><word>costectomy</word><word>costellate</word><word>coster</word><word>costerdom</word><word>costermonger</word><word>costicartilage</word><word>costicartilaginous</word><word>costicervical</word><word>costiferous</word><word>costiform</word><word>costing</word><word>costipulator</word><word>costispinal</word><word>costive</word><word>costively</word><word>costiveness</word><word>costless</word><word>costlessness</word><word>costliness</word><word>costly</word><word>costmary</word><word>costoabdominal</word><word>costoapical</word><word>costocentral</word><word>costochondral</word><word>costoclavicular</word><word>costocolic</word><word>costocoracoid</word><word>costodiaphragmatic</word><word>costogenic</word><word>costoinferior</word><word>costophrenic</word><word>costopleural</word><word>costopneumopexy</word><word>costopulmonary</word><word>costoscapular</word><word>costosternal</word><word>costosuperior</word><word>costothoracic</word><word>costotome</word><word>costotomy</word><word>costotrachelian</word><word>costotransversal</word><word>costotransverse</word><word>costovertebral</word><word>costoxiphoid</word><word>costraight</word><word>costrel</word><word>costula</word><word>costulation</word><word>costume</word><word>costumer</word><word>costumery</word><word>costumic</word><word>costumier</word><word>costumiere</word><word>costuming</word><word>costumist</word><word>costusroot</word><word>cosubject</word><word>cosubordinate</word><word>cosuffer</word><word>cosufferer</word><word>cosuggestion</word><word>cosuitor</word><word>cosurety</word><word>cosustain</word><word>coswearer</word><word>cosy</word><word>cosymmedian</word><word>cot</word><word>cotangent</word><word>cotangential</word><word>cotarius</word><word>cotarnine</word><word>cotch</word><word>cote</word><word>coteful</word><word>coteline</word><word>coteller</word><word>cotemporane</word><word>cotemporanean</word><word>cotemporaneous</word><word>cotemporaneously</word><word>cotemporary</word><word>cotenancy</word><word>cotenant</word><word>cotenure</word><word>coterell</word><word>coterie</word><word>coterminous</word><word>cotesian</word><word>coth</word><word>cothamore</word><word>cothe</word><word>cotheorist</word><word>cothish</word><word>cothon</word><word>cothurn</word></dict>