<dict><word>erosional</word><word>erosionist</word><word>erosive</word><word>erostrate</word><word>eroteme</word><word>erotesis</word><word>erotetic</word><word>erotic</word><word>erotica</word><word>erotical</word><word>erotically</word><word>eroticism</word><word>eroticize</word><word>eroticomania</word><word>erotism</word><word>erotogenesis</word><word>erotogenetic</word><word>erotogenic</word><word>erotogenicity</word><word>erotomania</word><word>erotomaniac</word><word>erotopath</word><word>erotopathic</word><word>erotopathy</word><word>erotylidae</word><word>erpetoichthys</word><word>erpetologist</word><word>err</word><word>errability</word><word>errable</word><word>errableness</word><word>errabund</word><word>errancy</word><word>errand</word><word>errant</word><word>errantia</word><word>errantly</word><word>errantness</word><word>errantry</word><word>errata</word><word>erratic</word><word>erratical</word><word>erratically</word><word>erraticalness</word><word>erraticism</word><word>erraticness</word><word>erratum</word><word>errhine</word><word>erring</word><word>erringly</word><word>errite</word><word>erroneous</word><word>erroneously</word><word>erroneousness</word><word>error</word><word>errorful</word><word>errorist</word><word>errorless</word><word>ers</word><word>ersar</word><word>ersatz</word><word>erse</word><word>ertebolle</word><word>erth</word><word>erthen</word><word>erthling</word><word>erthly</word><word>erubescence</word><word>erubescent</word><word>erubescite</word><word>eruc</word><word>eruca</word><word>eruca</word><word>erucic</word><word>eruciform</word><word>erucin</word><word>erucivorous</word><word>eruct</word><word>eructance</word><word>eructation</word><word>eructative</word><word>eruction</word><word>erudit</word><word>erudite</word><word>eruditely</word><word>eruditeness</word><word>eruditical</word><word>erudition</word><word>eruditional</word><word>eruditionist</word><word>erugate</word><word>erugation</word><word>erugatory</word><word>erumpent</word><word>erupt</word><word>eruption</word><word>eruptional</word><word>eruptive</word><word>eruptively</word><word>eruptiveness</word><word>eruptivity</word><word>ervenholder</word><word>ervipiame</word><word>ervum</word><word>erwinia</word><word>eryhtrism</word><word>erymanthian</word><word>eryngium</word><word>eryngo</word><word>eryon</word><word>eryops</word><word>erysibe</word><word>erysimum</word><word>erysipelas</word><word>erysipelatoid</word><word>erysipelatous</word><word>erysipeloid</word><word>erysipelothrix</word><word>erysipelous</word><word>erysiphaceae</word><word>erysiphe</word><word>erythea</word><word>erythema</word><word>erythematic</word><word>erythematous</word><word>erythemic</word><word>erythraea</word><word>erythraean</word><word>erythraeidae</word><word>erythrasma</word><word>erythrean</word><word>erythremia</word><word>erythremomelalgia</word><word>erythrene</word><word>erythrin</word><word>erythrina</word><word>erythrine</word><word>erythrinidae</word><word>erythrinus</word><word>erythrismal</word><word>erythristic</word><word>erythrite</word><word>erythritic</word><word>erythritol</word><word>erythroblast</word><word>erythroblastic</word><word>erythroblastosis</word><word>erythrocarpous</word><word>erythrocatalysis</word><word>erythrochaete</word><word>erythrochroic</word><word>erythrochroism</word><word>erythroclasis</word><word>erythroclastic</word><word>erythrocyte</word><word>erythrocytic</word><word>erythrocytoblast</word><word>erythrocytolysin</word><word>erythrocytolysis</word><word>erythrocytolytic</word><word>erythrocytometer</word><word>erythrocytorrhexis</word><word>erythrocytoschisis</word><word>erythrocytosis</word><word>erythrodegenerative</word><word>erythrodermia</word><word>erythrodextrin</word><word>erythrogenesis</word><word>erythrogenic</word><word>erythroglucin</word><word>erythrogonium</word><word>erythroid</word><word>erythrol</word><word>erythrolein</word><word>erythrolitmin</word><word>erythrolysin</word><word>erythrolysis</word><word>erythrolytic</word><word>erythromelalgia</word><word>erythron</word><word>erythroneocytosis</word><word>erythronium</word><word>erythronium</word><word>erythropenia</word><word>erythrophage</word><word>erythrophagous</word><word>erythrophilous</word><word>erythrophleine</word><word>erythrophobia</word><word>erythrophore</word><word>erythrophyll</word><word>erythrophyllin</word><word>erythropia</word><word>erythroplastid</word><word>erythropoiesis</word><word>erythropoietic</word><word>erythropsia</word><word>erythropsin</word><word>erythrorrhexis</word><word>erythroscope</word><word>erythrose</word><word>erythrosiderite</word><word>erythrosin</word><word>erythrosinophile</word><word>erythrosis</word><word>erythroxylaceae</word><word>erythroxylaceous</word><word>erythroxyline</word><word>erythroxylon</word><word>erythroxylum</word><word>erythrozincite</word><word>erythrozyme</word><word>erythrulose</word><word>eryx</word><word>es</word><word>esca</word><word>escadrille</word><word>escalade</word><word>escalader</word><word>escalado</word><word>escalan</word><word>escalate</word><word>escalator</word><word>escalator</word><word>escalin</word><word>escallonia</word><word>escalloniaceae</word><word>escalloniaceous</word><word>escalop</word><word>escaloped</word><word>escambio</word><word>escambron</word><word>escapable</word><word>escapade</word><word>escapage</word><word>escape</word><word>escapee</word><word>escapeful</word><word>escapeless</word><word>escapement</word><word>escaper</word><word>escapingly</word><word>escapism</word><word>escapist</word><word>escarbuncle</word><word>escargatoire</word><word>escarole</word><word>escarp</word><word>escarpment</word><word>eschalot</word></dict>