<dict><word>homemaker</word><word>homemaking</word><word>homeoblastic</word><word>homeochromatic</word><word>homeochromatism</word><word>homeochronous</word><word>homeocrystalline</word><word>homeogenic</word><word>homeogenous</word><word>homeoid</word><word>homeoidal</word><word>homeoidality</word><word>homeokinesis</word><word>homeokinetic</word><word>homeomerous</word><word>homeomorph</word><word>homeomorphic</word><word>homeomorphism</word><word>homeomorphous</word><word>homeomorphy</word><word>homeopath</word><word>homeopathic</word><word>homeopathically</word><word>homeopathician</word><word>homeopathicity</word><word>homeopathist</word><word>homeopathy</word><word>homeophony</word><word>homeoplasia</word><word>homeoplastic</word><word>homeoplasy</word><word>homeopolar</word><word>homeosis</word><word>homeostasis</word><word>homeostatic</word><word>homeotic</word><word>homeotransplant</word><word>homeotransplantation</word><word>homeotype</word><word>homeotypic</word><word>homeotypical</word><word>homeowner</word><word>homeozoic</word><word>homer</word><word>homer</word><word>homerian</word><word>homeric</word><word>homerical</word><word>homerically</word><word>homerid</word><word>homeridae</word><word>homeridian</word><word>homerist</word><word>homerologist</word><word>homerology</word><word>homeromastix</word><word>homeseeker</word><word>homesick</word><word>homesickly</word><word>homesickness</word><word>homesite</word><word>homesome</word><word>homespun</word><word>homestall</word><word>homestead</word><word>homesteader</word><word>homester</word><word>homestretch</word><word>homeward</word><word>homewardly</word><word>homework</word><word>homeworker</word><word>homewort</word><word>homey</word><word>homeyness</word><word>homicidal</word><word>homicidally</word><word>homicide</word><word>homicidious</word><word>homiculture</word><word>homilete</word><word>homiletic</word><word>homiletical</word><word>homiletically</word><word>homiletics</word><word>homiliarium</word><word>homiliary</word><word>homilist</word><word>homilite</word><word>homilize</word><word>homily</word><word>hominal</word><word>hominess</word><word>hominian</word><word>hominid</word><word>hominidae</word><word>hominiform</word><word>hominify</word><word>hominine</word><word>hominisection</word><word>hominivorous</word><word>hominoid</word><word>hominy</word><word>homish</word><word>homishness</word><word>homo</word><word>homoanisaldehyde</word><word>homoanisic</word><word>homoarecoline</word><word>homobaric</word><word>homoblastic</word><word>homoblasty</word><word>homocarpous</word><word>homocategoric</word><word>homocentric</word><word>homocentrical</word><word>homocentrically</word><word>homocerc</word><word>homocercal</word><word>homocercality</word><word>homocercy</word><word>homocerebrin</word><word>homochiral</word><word>homochlamydeous</word><word>homochromatic</word><word>homochromatism</word><word>homochrome</word><word>homochromic</word><word>homochromosome</word><word>homochromous</word><word>homochromy</word><word>homochronous</word><word>homoclinal</word><word>homocline</word><word>homocoela</word><word>homocoelous</word><word>homocreosol</word><word>homocyclic</word><word>homodermic</word><word>homodermy</word><word>homodont</word><word>homodontism</word><word>homodox</word><word>homodoxian</word><word>homodromal</word><word>homodrome</word><word>homodromous</word><word>homodromy</word><word>homodynamic</word><word>homodynamous</word><word>homodynamy</word><word>homodyne</word><word>homoean</word><word>homoeanism</word><word>homoecious</word><word>homoeoarchy</word><word>homoeoblastic</word><word>homoeochromatic</word><word>homoeochronous</word><word>homoeocrystalline</word><word>homoeogenic</word><word>homoeogenous</word><word>homoeography</word><word>homoeokinesis</word><word>homoeomerae</word><word>homoeomeri</word><word>homoeomeria</word><word>homoeomerian</word><word>homoeomerianism</word><word>homoeomeric</word><word>homoeomerical</word><word>homoeomerous</word><word>homoeomery</word><word>homoeomorph</word><word>homoeomorphic</word><word>homoeomorphism</word><word>homoeomorphous</word><word>homoeomorphy</word><word>homoeopath</word><word>homoeopathic</word><word>homoeopathically</word><word>homoeopathician</word><word>homoeopathicity</word><word>homoeopathist</word><word>homoeopathy</word><word>homoeophony</word><word>homoeophyllous</word><word>homoeoplasia</word><word>homoeoplastic</word><word>homoeoplasy</word><word>homoeopolar</word><word>homoeosis</word><word>homoeotel</word><word>homoeoteleutic</word><word>homoeoteleuton</word><word>homoeotic</word><word>homoeotopy</word><word>homoeotype</word><word>homoeotypic</word><word>homoeotypical</word><word>homoeozoic</word><word>homoerotic</word><word>homoerotism</word><word>homofermentative</word><word>homogametic</word><word>homogamic</word><word>homogamous</word><word>homogamy</word><word>homogangliate</word><word>homogen</word><word>homogenate</word><word>homogene</word><word>homogeneal</word><word>homogenealness</word><word>homogeneate</word><word>homogeneity</word><word>homogeneization</word><word>homogeneize</word><word>homogeneous</word><word>homogeneously</word><word>homogeneousness</word><word>homogenesis</word><word>homogenetic</word><word>homogenetical</word><word>homogenic</word><word>homogenization</word><word>homogenize</word><word>homogenizer</word><word>homogenous</word><word>homogentisic</word><word>homogeny</word><word>homoglot</word><word>homogone</word><word>homogonous</word><word>homogonously</word><word>homogony</word><word>homograft</word><word>homograph</word><word>homographic</word><word>homography</word><word>homohedral</word><word>homoiotherm</word><word>homoiothermal</word><word>homoiothermic</word><word>homoiothermism</word><word>homoiothermous</word><word>homoiousia</word><word>homoiousian</word><word>homoiousian</word><word>homoiousianism</word></dict>