<dict><word>indianan</word><word>indianeer</word><word>indianesque</word><word>indianhood</word><word>indianian</word><word>indianism</word><word>indianist</word><word>indianite</word><word>indianization</word><word>indianize</word><word>indic</word><word>indic</word><word>indicable</word><word>indican</word><word>indicant</word><word>indicanuria</word><word>indicate</word><word>indication</word><word>indicative</word><word>indicatively</word><word>indicator</word><word>indicatoridae</word><word>indicatorinae</word><word>indicatory</word><word>indicatrix</word><word>indices</word><word>indicia</word><word>indicial</word><word>indicible</word><word>indicium</word><word>indicolite</word><word>indict</word><word>indictable</word><word>indictably</word><word>indictee</word><word>indicter</word><word>indiction</word><word>indictional</word><word>indictive</word><word>indictment</word><word>indictor</word><word>indies</word><word>indiferous</word><word>indifference</word><word>indifferency</word><word>indifferent</word><word>indifferential</word><word>indifferentism</word><word>indifferentist</word><word>indifferentistic</word><word>indifferently</word><word>indigena</word><word>indigenal</word><word>indigenate</word><word>indigence</word><word>indigency</word><word>indigene</word><word>indigeneity</word><word>indigenismo</word><word>indigenist</word><word>indigenity</word><word>indigenous</word><word>indigenously</word><word>indigenousness</word><word>indigent</word><word>indigently</word><word>indigested</word><word>indigestedness</word><word>indigestibility</word><word>indigestible</word><word>indigestibleness</word><word>indigestibly</word><word>indigestion</word><word>indigestive</word><word>indigitamenta</word><word>indigitate</word><word>indigitation</word><word>indign</word><word>indignance</word><word>indignancy</word><word>indignant</word><word>indignantly</word><word>indignation</word><word>indignatory</word><word>indignify</word><word>indignity</word><word>indignly</word><word>indigo</word><word>indigoberry</word><word>indigofera</word><word>indigoferous</word><word>indigoid</word><word>indigotic</word><word>indigotin</word><word>indigotindisulphonic</word><word>indiguria</word><word>indimensible</word><word>indimensional</word><word>indiminishable</word><word>indimple</word><word>indirect</word><word>indirected</word><word>indirection</word><word>indirectly</word><word>indirectness</word><word>indirubin</word><word>indiscernibility</word><word>indiscernible</word><word>indiscernibleness</word><word>indiscernibly</word><word>indiscerptibility</word><word>indiscerptible</word><word>indiscerptibleness</word><word>indiscerptibly</word><word>indisciplinable</word><word>indiscipline</word><word>indisciplined</word><word>indiscoverable</word><word>indiscoverably</word><word>indiscovered</word><word>indiscreet</word><word>indiscreetly</word><word>indiscreetness</word><word>indiscrete</word><word>indiscretely</word><word>indiscretion</word><word>indiscretionary</word><word>indiscriminate</word><word>indiscriminated</word><word>indiscriminately</word><word>indiscriminateness</word><word>indiscriminating</word><word>indiscriminatingly</word><word>indiscrimination</word><word>indiscriminative</word><word>indiscriminatively</word><word>indiscriminatory</word><word>indiscussable</word><word>indiscussible</word><word>indispellable</word><word>indispensability</word><word>indispensable</word><word>indispensableness</word><word>indispensably</word><word>indispose</word><word>indisposed</word><word>indisposedness</word><word>indisposition</word><word>indisputability</word><word>indisputable</word><word>indisputableness</word><word>indisputably</word><word>indissipable</word><word>indissociable</word><word>indissolubility</word><word>indissoluble</word><word>indissolubleness</word><word>indissolubly</word><word>indissolute</word><word>indissolvability</word><word>indissolvable</word><word>indissolvableness</word><word>indissolvably</word><word>indissuadable</word><word>indissuadably</word><word>indistinct</word><word>indistinction</word><word>indistinctive</word><word>indistinctively</word><word>indistinctiveness</word><word>indistinctly</word><word>indistinctness</word><word>indistinguishability</word><word>indistinguishable</word><word>indistinguishableness</word><word>indistinguishably</word><word>indistinguished</word><word>indistortable</word><word>indistributable</word><word>indisturbable</word><word>indisturbance</word><word>indisturbed</word><word>indite</word><word>inditement</word><word>inditer</word><word>indium</word><word>indivertible</word><word>indivertibly</word><word>individable</word><word>individua</word><word>individual</word><word>individualism</word><word>individualist</word><word>individualistic</word><word>individualistically</word><word>individuality</word><word>individualization</word><word>individualize</word><word>individualizer</word><word>individualizingly</word><word>individually</word><word>individuate</word><word>individuation</word><word>individuative</word><word>individuator</word><word>individuity</word><word>individuum</word><word>indivinable</word><word>indivisibility</word><word>indivisible</word><word>indivisibleness</word><word>indivisibly</word><word>indivision</word><word>indocibility</word><word>indocible</word><word>indocibleness</word><word>indocile</word><word>indocility</word><word>indoctrinate</word><word>indoctrination</word><word>indoctrinator</word><word>indoctrine</word><word>indoctrinization</word><word>indoctrinize</word><word>indogaea</word><word>indogaean</word><word>indogen</word><word>indogenide</word><word>indole</word><word>indolence</word><word>indolent</word><word>indolently</word><word>indoles</word><word>indoline</word><word>indologian</word><word>indologist</word><word>indologue</word><word>indology</word><word>indoloid</word><word>indolyl</word><word>indomitability</word><word>indomitable</word><word>indomitableness</word><word>indomitably</word><word>indone</word><word>indonesian</word><word>indoor</word><word>indoors</word><word>indophenin</word><word>indophenol</word></dict>