<dict><word>podger</word><word>podgily</word><word>podginess</word><word>podgy</word><word>podial</word><word>podiatrist</word><word>podiatry</word><word>podical</word><word>podiceps</word><word>podices</word><word>podicipedidae</word><word>podilegous</word><word>podite</word><word>poditic</word><word>poditti</word><word>podium</word><word>podler</word><word>podley</word><word>podlike</word><word>podobranch</word><word>podobranchia</word><word>podobranchial</word><word>podobranchiate</word><word>podocarp</word><word>podocarpaceae</word><word>podocarpineae</word><word>podocarpous</word><word>podocarpus</word><word>podocephalous</word><word>pododerm</word><word>pododynia</word><word>podogyn</word><word>podogyne</word><word>podogynium</word><word>podolian</word><word>podolite</word><word>podology</word><word>podomancy</word><word>podomere</word><word>podometer</word><word>podometry</word><word>podophrya</word><word>podophryidae</word><word>podophthalma</word><word>podophthalmata</word><word>podophthalmate</word><word>podophthalmatous</word><word>podophthalmia</word><word>podophthalmian</word><word>podophthalmic</word><word>podophthalmite</word><word>podophthalmitic</word><word>podophthalmous</word><word>podophyllaceae</word><word>podophyllic</word><word>podophyllin</word><word>podophyllotoxin</word><word>podophyllous</word><word>podophyllum</word><word>podophyllum</word><word>podoscaph</word><word>podoscapher</word><word>podoscopy</word><word>podosomata</word><word>podosomatous</word><word>podosperm</word><word>podosphaera</word><word>podostemaceae</word><word>podostemaceous</word><word>podostemad</word><word>podostemon</word><word>podostemonaceae</word><word>podostemonaceous</word><word>podostomata</word><word>podostomatous</word><word>podotheca</word><word>podothecal</word><word>podozamites</word><word>podsnap</word><word>podsnappery</word><word>podsol</word><word>podsolic</word><word>podsolization</word><word>podsolize</word><word>podunk</word><word>podura</word><word>poduran</word><word>podurid</word><word>poduridae</word><word>podware</word><word>podzol</word><word>podzolic</word><word>podzolization</word><word>podzolize</word><word>poe</word><word>poecile</word><word>poeciliidae</word><word>poecilitic</word><word>poecilocyttares</word><word>poecilocyttarous</word><word>poecilogonous</word><word>poecilogony</word><word>poecilomere</word><word>poecilonym</word><word>poecilonymic</word><word>poecilonymy</word><word>poecilopod</word><word>poecilopoda</word><word>poecilopodous</word><word>poem</word><word>poematic</word><word>poemet</word><word>poemlet</word><word>poephaga</word><word>poephagous</word><word>poephagus</word><word>poesie</word><word>poesiless</word><word>poesis</word><word>poesy</word><word>poet</word><word>poetaster</word><word>poetastering</word><word>poetasterism</word><word>poetastery</word><word>poetastress</word><word>poetastric</word><word>poetastrical</word><word>poetastry</word><word>poetcraft</word><word>poetdom</word><word>poetesque</word><word>poetess</word><word>poethood</word><word>poetic</word><word>poetical</word><word>poeticality</word><word>poetically</word><word>poeticalness</word><word>poeticism</word><word>poeticize</word><word>poeticness</word><word>poetics</word><word>poeticule</word><word>poetito</word><word>poetization</word><word>poetize</word><word>poetizer</word><word>poetless</word><word>poetlike</word><word>poetling</word><word>poetly</word><word>poetomachia</word><word>poetress</word><word>poetry</word><word>poetryless</word><word>poetship</word><word>poetwise</word><word>pogamoggan</word><word>pogge</word><word>poggy</word><word>pogo</word><word>pogonatum</word><word>pogonia</word><word>pogoniasis</word><word>pogoniate</word><word>pogonion</word><word>pogonip</word><word>pogoniris</word><word>pogonite</word><word>pogonological</word><word>pogonologist</word><word>pogonology</word><word>pogonotomy</word><word>pogonotrophy</word><word>pogrom</word><word>pogromist</word><word>pogromize</word><word>pogy</word><word>poh</word><word>poha</word><word>pohickory</word><word>pohna</word><word>pohutukawa</word><word>poi</word><word>poiana</word><word>poictesme</word><word>poietic</word><word>poignance</word><word>poignancy</word><word>poignant</word><word>poignantly</word><word>poignet</word><word>poikilitic</word><word>poikiloblast</word><word>poikiloblastic</word><word>poikilocyte</word><word>poikilocythemia</word><word>poikilocytosis</word><word>poikilotherm</word><word>poikilothermic</word><word>poikilothermism</word><word>poil</word><word>poilu</word><word>poimenic</word><word>poimenics</word><word>poinciana</word><word>poind</word><word>poindable</word><word>poinder</word><word>poinding</word><word>poinsettia</word><word>point</word><word>pointable</word><word>pointage</word><word>pointed</word><word>pointedly</word><word>pointedness</word><word>pointel</word><word>pointer</word><word>pointful</word><word>pointfully</word><word>pointfulness</word><word>pointillism</word><word>pointillist</word><word>pointing</word><word>pointingly</word><word>pointless</word><word>pointlessly</word><word>pointlessness</word><word>pointlet</word><word>pointleted</word><word>pointmaker</word><word>pointman</word><word>pointment</word><word>pointrel</word><word>pointsman</word><word>pointswoman</word><word>pointways</word><word>pointwise</word><word>pointy</word><word>poisable</word><word>poise</word><word>poised</word><word>poiser</word><word>poison</word><word>poisonable</word><word>poisonful</word><word>poisonfully</word><word>poisoning</word></dict>