<dict><word>pontederiaceae</word><word>pontederiaceous</word><word>pontee</word><word>pontes</word><word>pontianak</word><word>pontic</word><word>pontic</word><word>ponticello</word><word>ponticular</word><word>ponticulus</word><word>pontifex</word><word>pontiff</word><word>pontific</word><word>pontifical</word><word>pontificalia</word><word>pontificalibus</word><word>pontificality</word><word>pontifically</word><word>pontificate</word><word>pontification</word><word>pontifices</word><word>pontificial</word><word>pontificially</word><word>pontificious</word><word>pontify</word><word>pontil</word><word>pontile</word><word>pontin</word><word>pontine</word><word>pontine</word><word>pontist</word><word>pontlevis</word><word>ponto</word><word>pontocaspian</word><word>pontocerebellar</word><word>ponton</word><word>pontonier</word><word>pontoon</word><word>pontooneer</word><word>pontooner</word><word>pontooning</word><word>pontvolant</word><word>pony</word><word>ponzite</word><word>pooa</word><word>pooch</word><word>pooder</word><word>poodle</word><word>poodledom</word><word>poodleish</word><word>poodleship</word><word>poof</word><word>poogye</word><word>pooh</word><word>poohpoohist</word><word>pook</word><word>pooka</word><word>pookaun</word><word>pookoo</word><word>pool</word><word>pooler</word><word>pooli</word><word>poolroom</word><word>poolroot</word><word>poolside</word><word>poolwort</word><word>pooly</word><word>poon</word><word>poonac</word><word>poonga</word><word>poonghie</word><word>poop</word><word>pooped</word><word>poophyte</word><word>poophytic</word><word>poor</word><word>poorhouse</word><word>poorish</word><word>poorliness</word><word>poorling</word><word>poorly</word><word>poorlyish</word><word>poormaster</word><word>poorness</word><word>poorweed</word><word>poorwill</word><word>poot</word><word>pop</word><word>pop</word><word>popadam</word><word>popal</word><word>popcorn</word><word>popdock</word><word>pope</word><word>popean</word><word>popedom</word><word>popeholy</word><word>popehood</word><word>popeism</word><word>popeler</word><word>popeless</word><word>popelike</word><word>popeline</word><word>popely</word><word>popery</word><word>popeship</word><word>popess</word><word>popeye</word><word>popeyed</word><word>popglove</word><word>popgun</word><word>popgunner</word><word>popgunnery</word><word>popian</word><word>popify</word><word>popinac</word><word>popinjay</word><word>popish</word><word>popish</word><word>popishly</word><word>popishness</word><word>popjoy</word><word>poplar</word><word>poplared</word><word>poplilia</word><word>poplin</word><word>poplinette</word><word>popliteal</word><word>popliteus</word><word>poplolly</word><word>popocracy</word><word>popocrat</word><word>popolari</word><word>popoloco</word><word>popomastic</word><word>popover</word><word>popovets</word><word>poppa</word><word>poppability</word><word>poppable</word><word>poppean</word><word>poppel</word><word>popper</word><word>poppet</word><word>poppethead</word><word>poppied</word><word>poppin</word><word>popple</word><word>popply</word><word>poppy</word><word>poppycock</word><word>poppycockish</word><word>poppyfish</word><word>poppyhead</word><word>poppylike</word><word>poppywort</word><word>popshop</word><word>populace</word><word>popular</word><word>popularism</word><word>popularist</word><word>popularity</word><word>popularization</word><word>popularize</word><word>popularizer</word><word>popularly</word><word>popularness</word><word>populate</word><word>population</word><word>populational</word><word>populationist</word><word>populationistic</word><word>populationless</word><word>populator</word><word>populicide</word><word>populin</word><word>populism</word><word>populist</word><word>populistic</word><word>populous</word><word>populously</word><word>populousness</word><word>populus</word><word>popweed</word><word>poral</word><word>porbeagle</word><word>porcate</word><word>porcated</word><word>porcelain</word><word>porcelainization</word><word>porcelainize</word><word>porcelainlike</word><word>porcelainous</word><word>porcelaneous</word><word>porcelanic</word><word>porcelanite</word><word>porcelanous</word><word>porcellana</word><word>porcellanian</word><word>porcellanid</word><word>porcellanidae</word><word>porcellanize</word><word>porch</word><word>porched</word><word>porching</word><word>porchless</word><word>porchlike</word><word>porcine</word><word>porcula</word><word>porcupine</word><word>porcupinish</word><word>pore</word><word>pored</word><word>porelike</word><word>porella</word><word>porencephalia</word><word>porencephalic</word><word>porencephalitis</word><word>porencephalon</word><word>porencephalous</word><word>porencephalus</word><word>porencephaly</word><word>porer</word><word>porge</word><word>porger</word><word>porgy</word><word>poria</word><word>poricidal</word><word>porifera</word><word>poriferal</word><word>poriferan</word><word>poriferous</word><word>poriform</word><word>porimania</word><word>poriness</word><word>poring</word><word>poringly</word><word>poriomanic</word><word>porism</word><word>porismatic</word><word>porismatical</word><word>porismatically</word><word>poristic</word><word>poristical</word><word>porite</word><word>porites</word><word>poritidae</word><word>poritoid</word><word>pork</word><word>porkburger</word></dict>