<dict><word>rearmament</word><word>rearmost</word><word>rearousal</word><word>rearouse</word><word>rearrange</word><word>rearrangeable</word><word>rearrangement</word><word>rearranger</word><word>rearray</word><word>rearrest</word><word>rearrival</word><word>rearrive</word><word>rearward</word><word>rearwardly</word><word>rearwardness</word><word>rearwards</word><word>reascend</word><word>reascendancy</word><word>reascendant</word><word>reascendency</word><word>reascendent</word><word>reascension</word><word>reascensional</word><word>reascent</word><word>reascertain</word><word>reascertainment</word><word>reashlar</word><word>reasiness</word><word>reask</word><word>reason</word><word>reasonability</word><word>reasonable</word><word>reasonableness</word><word>reasonably</word><word>reasoned</word><word>reasonedly</word><word>reasoner</word><word>reasoning</word><word>reasoningly</word><word>reasonless</word><word>reasonlessly</word><word>reasonlessness</word><word>reasonproof</word><word>reaspire</word><word>reassail</word><word>reassault</word><word>reassay</word><word>reassemblage</word><word>reassemble</word><word>reassembly</word><word>reassent</word><word>reassert</word><word>reassertion</word><word>reassertor</word><word>reassess</word><word>reassessment</word><word>reasseverate</word><word>reassign</word><word>reassignation</word><word>reassignment</word><word>reassimilate</word><word>reassimilation</word><word>reassist</word><word>reassistance</word><word>reassociate</word><word>reassociation</word><word>reassort</word><word>reassortment</word><word>reassume</word><word>reassumption</word><word>reassurance</word><word>reassure</word><word>reassured</word><word>reassuredly</word><word>reassurement</word><word>reassurer</word><word>reassuring</word><word>reassuringly</word><word>reastiness</word><word>reastonish</word><word>reastonishment</word><word>reastray</word><word>reasty</word><word>reasy</word><word>reattach</word><word>reattachment</word><word>reattack</word><word>reattain</word><word>reattainment</word><word>reattempt</word><word>reattend</word><word>reattendance</word><word>reattention</word><word>reattentive</word><word>reattest</word><word>reattire</word><word>reattract</word><word>reattraction</word><word>reattribute</word><word>reattribution</word><word>reatus</word><word>reaudit</word><word>reauthenticate</word><word>reauthentication</word><word>reauthorization</word><word>reauthorize</word><word>reavail</word><word>reavailable</word><word>reave</word><word>reaver</word><word>reavoid</word><word>reavoidance</word><word>reavouch</word><word>reavow</word><word>reawait</word><word>reawake</word><word>reawaken</word><word>reawakening</word><word>reawakenment</word><word>reaward</word><word>reaware</word><word>reb</word><word>rebab</word><word>reback</word><word>rebag</word><word>rebait</word><word>rebake</word><word>rebalance</word><word>rebale</word><word>reballast</word><word>reballot</word><word>reban</word><word>rebandage</word><word>rebanish</word><word>rebanishment</word><word>rebankrupt</word><word>rebankruptcy</word><word>rebaptism</word><word>rebaptismal</word><word>rebaptization</word><word>rebaptize</word><word>rebaptizer</word><word>rebar</word><word>rebarbarization</word><word>rebarbarize</word><word>rebarbative</word><word>rebargain</word><word>rebase</word><word>rebasis</word><word>rebatable</word><word>rebate</word><word>rebateable</word><word>rebatement</word><word>rebater</word><word>rebathe</word><word>rebato</word><word>rebawl</word><word>rebeamer</word><word>rebear</word><word>rebeat</word><word>rebeautify</word><word>rebec</word><word>rebecca</word><word>rebeccaism</word><word>rebeccaites</word><word>rebeck</word><word>rebecome</word><word>rebed</word><word>rebeg</word><word>rebeget</word><word>rebeggar</word><word>rebegin</word><word>rebeginner</word><word>rebeginning</word><word>rebeguile</word><word>rebehold</word><word>rebekah</word><word>rebel</word><word>rebeldom</word><word>rebelief</word><word>rebelieve</word><word>rebeller</word><word>rebellike</word><word>rebellion</word><word>rebellious</word><word>rebelliously</word><word>rebelliousness</word><word>rebellow</word><word>rebelly</word><word>rebelong</word><word>rebelove</word><word>rebelproof</word><word>rebemire</word><word>rebend</word><word>rebenediction</word><word>rebenefit</word><word>rebeset</word><word>rebesiege</word><word>rebestow</word><word>rebestowal</word><word>rebetake</word><word>rebetray</word><word>rebewail</word><word>rebia</word><word>rebias</word><word>rebid</word><word>rebill</word><word>rebillet</word><word>rebilling</word><word>rebind</word><word>rebirth</word><word>rebite</word><word>reblade</word><word>reblame</word><word>reblast</word><word>rebleach</word><word>reblend</word><word>rebless</word><word>reblock</word><word>rebloom</word><word>reblossom</word><word>reblot</word><word>reblow</word><word>reblue</word><word>rebluff</word><word>reblunder</word><word>reboant</word><word>reboantic</word><word>reboard</word><word>reboast</word><word>rebob</word><word>reboil</word><word>reboiler</word><word>reboise</word><word>reboisement</word><word>rebold</word><word>rebolt</word><word>rebone</word><word>rebook</word><word>rebop</word><word>rebore</word><word>reborn</word><word>reborrow</word><word>rebottle</word><word>reboulia</word><word>rebounce</word><word>rebound</word><word>reboundable</word><word>rebounder</word><word>reboundingness</word></dict>