<dict><word>spondylarthritis</word><word>spondylarthrocace</word><word>spondylexarthrosis</word><word>spondylic</word><word>spondylid</word><word>spondylidae</word><word>spondylioid</word><word>spondylitic</word><word>spondylitis</word><word>spondylium</word><word>spondylizema</word><word>spondylocace</word><word>spondylocladium</word><word>spondylodiagnosis</word><word>spondylodidymia</word><word>spondylodymus</word><word>spondyloid</word><word>spondylolisthesis</word><word>spondylolisthetic</word><word>spondylopathy</word><word>spondylopyosis</word><word>spondyloschisis</word><word>spondylosis</word><word>spondylosyndesis</word><word>spondylotherapeutics</word><word>spondylotherapist</word><word>spondylotherapy</word><word>spondylotomy</word><word>spondylous</word><word>spondylus</word><word>spondylus</word><word>spong</word><word>sponge</word><word>spongecake</word><word>sponged</word><word>spongeful</word><word>spongeless</word><word>spongelet</word><word>spongelike</word><word>spongeous</word><word>spongeproof</word><word>sponger</word><word>spongewood</word><word>spongiae</word><word>spongian</word><word>spongicolous</word><word>spongiculture</word><word>spongida</word><word>spongiferous</word><word>spongiform</word><word>spongiidae</word><word>spongilla</word><word>spongillid</word><word>spongillidae</word><word>spongilline</word><word>spongily</word><word>spongin</word><word>sponginblast</word><word>sponginblastic</word><word>sponginess</word><word>sponging</word><word>spongingly</word><word>spongioblast</word><word>spongioblastoma</word><word>spongiocyte</word><word>spongiolin</word><word>spongiopilin</word><word>spongioplasm</word><word>spongioplasmic</word><word>spongiose</word><word>spongiosity</word><word>spongiousness</word><word>spongiozoa</word><word>spongiozoon</word><word>spongoblast</word><word>spongoblastic</word><word>spongoid</word><word>spongology</word><word>spongophore</word><word>spongospora</word><word>spongy</word><word>sponsal</word><word>sponsalia</word><word>sponsibility</word><word>sponsible</word><word>sponsing</word><word>sponsion</word><word>sponsional</word><word>sponson</word><word>sponsor</word><word>sponsorial</word><word>sponsorship</word><word>sponspeck</word><word>spontaneity</word><word>spontaneous</word><word>spontaneously</word><word>spontaneousness</word><word>spontoon</word><word>spoof</word><word>spoofer</word><word>spoofery</word><word>spoofish</word><word>spook</word><word>spookdom</word><word>spookery</word><word>spookily</word><word>spookiness</word><word>spookish</word><word>spookism</word><word>spookist</word><word>spookological</word><word>spookologist</word><word>spookology</word><word>spooky</word><word>spool</word><word>spooler</word><word>spoolful</word><word>spoollike</word><word>spoolwood</word><word>spoom</word><word>spoon</word><word>spoonbill</word><word>spoondrift</word><word>spooner</word><word>spoonerism</word><word>spooneyism</word><word>spooneyly</word><word>spooneyness</word><word>spoonflower</word><word>spoonful</word><word>spoonhutch</word><word>spoonily</word><word>spooniness</word><word>spooning</word><word>spoonism</word><word>spoonless</word><word>spoonlike</word><word>spoonmaker</word><word>spoonmaking</word><word>spoonways</word><word>spoonwood</word><word>spoony</word><word>spoonyism</word><word>spoor</word><word>spoorer</word><word>spoot</word><word>spor</word><word>sporabola</word><word>sporaceous</word><word>sporades</word><word>sporadial</word><word>sporadic</word><word>sporadical</word><word>sporadically</word><word>sporadicalness</word><word>sporadicity</word><word>sporadism</word><word>sporadosiderite</word><word>sporal</word><word>sporange</word><word>sporangia</word><word>sporangial</word><word>sporangidium</word><word>sporangiferous</word><word>sporangiform</word><word>sporangioid</word><word>sporangiola</word><word>sporangiole</word><word>sporangiolum</word><word>sporangiophore</word><word>sporangiospore</word><word>sporangite</word><word>sporangites</word><word>sporangium</word><word>sporation</word><word>spore</word><word>spored</word><word>sporeformer</word><word>sporeforming</word><word>sporeling</word><word>sporicide</word><word>sporid</word><word>sporidesm</word><word>sporidia</word><word>sporidial</word><word>sporidiferous</word><word>sporidiole</word><word>sporidiolum</word><word>sporidium</word><word>sporiferous</word><word>sporification</word><word>sporiparity</word><word>sporiparous</word><word>sporoblast</word><word>sporobolus</word><word>sporocarp</word><word>sporocarpium</word><word>sporochnaceae</word><word>sporochnus</word><word>sporocyst</word><word>sporocystic</word><word>sporocystid</word><word>sporocyte</word><word>sporodochia</word><word>sporodochium</word><word>sporoduct</word><word>sporogenesis</word><word>sporogenic</word><word>sporogenous</word><word>sporogeny</word><word>sporogone</word><word>sporogonial</word><word>sporogonic</word><word>sporogonium</word><word>sporogony</word><word>sporoid</word><word>sporologist</word><word>sporomycosis</word><word>sporont</word><word>sporophore</word><word>sporophoric</word><word>sporophorous</word><word>sporophydium</word><word>sporophyll</word><word>sporophyllary</word><word>sporophyllum</word><word>sporophyte</word><word>sporophytic</word><word>sporoplasm</word><word>sporosac</word><word>sporostegium</word><word>sporostrote</word><word>sporotrichosis</word><word>sporotrichotic</word><word>sporotrichum</word><word>sporous</word><word>sporozoa</word><word>sporozoal</word><word>sporozoan</word><word>sporozoic</word><word>sporozoite</word><word>sporozoon</word><word>sporran</word><word>sport</word><word>sportability</word><word>sportable</word><word>sportance</word><word>sporter</word><word>sportful</word><word>sportfully</word></dict>