<dict><word>stageably</word><word>stagecoach</word><word>stagecoaching</word><word>stagecraft</word><word>staged</word><word>stagedom</word><word>stagehand</word><word>stagehouse</word><word>stageland</word><word>stagelike</word><word>stageman</word><word>stager</word><word>stagery</word><word>stagese</word><word>stagewise</word><word>stageworthy</word><word>stagewright</word><word>staggard</word><word>staggart</word><word>staggarth</word><word>stagger</word><word>staggerbush</word><word>staggerer</word><word>staggering</word><word>staggeringly</word><word>staggers</word><word>staggerweed</word><word>staggerwort</word><word>staggery</word><word>staggie</word><word>staggy</word><word>staghead</word><word>staghorn</word><word>staghound</word><word>staghunt</word><word>staghunter</word><word>staghunting</word><word>stagiary</word><word>stagily</word><word>staginess</word><word>staging</word><word>stagirite</word><word>stagiritic</word><word>staglike</word><word>stagmometer</word><word>stagnance</word><word>stagnancy</word><word>stagnant</word><word>stagnantly</word><word>stagnantness</word><word>stagnate</word><word>stagnation</word><word>stagnatory</word><word>stagnature</word><word>stagnicolous</word><word>stagnize</word><word>stagnum</word><word>stagonospora</word><word>stagskin</word><word>stagworm</word><word>stagy</word><word>stahlhelm</word><word>stahlhelmer</word><word>stahlhelmist</word><word>stahlian</word><word>stahlianism</word><word>stahlism</word><word>staia</word><word>staid</word><word>staidly</word><word>staidness</word><word>stain</word><word>stainability</word><word>stainable</word><word>stainableness</word><word>stainably</word><word>stainer</word><word>stainful</word><word>stainierite</word><word>staining</word><word>stainless</word><word>stainlessly</word><word>stainlessness</word><word>stainproof</word><word>staio</word><word>stair</word><word>stairbeak</word><word>stairbuilder</word><word>stairbuilding</word><word>staircase</word><word>staired</word><word>stairhead</word><word>stairless</word><word>stairlike</word><word>stairstep</word><word>stairway</word><word>stairwise</word><word>stairwork</word><word>stairy</word><word>staith</word><word>staithman</word><word>staiver</word><word>stake</word><word>stakehead</word><word>stakeholder</word><word>stakemaster</word><word>staker</word><word>stakerope</word><word>stakhanovism</word><word>stakhanovite</word><word>stalactic</word><word>stalactical</word><word>stalactiform</word><word>stalactital</word><word>stalactite</word><word>stalactited</word><word>stalactitic</word><word>stalactitical</word><word>stalactitically</word><word>stalactitiform</word><word>stalactitious</word><word>stalagma</word><word>stalagmite</word><word>stalagmitic</word><word>stalagmitical</word><word>stalagmitically</word><word>stalagmometer</word><word>stalagmometric</word><word>stalagmometry</word><word>stale</word><word>stalely</word><word>stalemate</word><word>staleness</word><word>staling</word><word>stalinism</word><word>stalinist</word><word>stalinite</word><word>stalk</word><word>stalkable</word><word>stalked</word><word>stalker</word><word>stalkily</word><word>stalkiness</word><word>stalking</word><word>stalkingly</word><word>stalkless</word><word>stalklet</word><word>stalklike</word><word>stalko</word><word>stalky</word><word>stall</word><word>stallage</word><word>stallar</word><word>stallboard</word><word>stallenger</word><word>staller</word><word>stallership</word><word>stalling</word><word>stallion</word><word>stallionize</word><word>stallman</word><word>stallment</word><word>stalwart</word><word>stalwartism</word><word>stalwartize</word><word>stalwartly</word><word>stalwartness</word><word>stam</word><word>stambha</word><word>stambouline</word><word>stamen</word><word>stamened</word><word>stamin</word><word>stamina</word><word>staminal</word><word>staminate</word><word>stamineal</word><word>stamineous</word><word>staminiferous</word><word>staminigerous</word><word>staminode</word><word>staminodium</word><word>staminody</word><word>stammel</word><word>stammer</word><word>stammerer</word><word>stammering</word><word>stammeringly</word><word>stammeringness</word><word>stammerwort</word><word>stamnos</word><word>stamp</word><word>stampable</word><word>stampage</word><word>stampedable</word><word>stampede</word><word>stampeder</word><word>stampedingly</word><word>stampee</word><word>stamper</word><word>stampery</word><word>stamphead</word><word>stampian</word><word>stamping</word><word>stample</word><word>stampless</word><word>stampman</word><word>stampsman</word><word>stampweed</word><word>stance</word><word>stanch</word><word>stanchable</word><word>stanchel</word><word>stancheled</word><word>stancher</word><word>stanchion</word><word>stanchless</word><word>stanchly</word><word>stanchness</word><word>stand</word><word>standage</word><word>standard</word><word>standardbred</word><word>standardizable</word><word>standardization</word><word>standardize</word><word>standardized</word><word>standardizer</word><word>standardwise</word><word>standee</word><word>standel</word><word>standelwelks</word><word>standelwort</word><word>stander</word><word>standergrass</word><word>standerwort</word><word>standfast</word><word>standing</word><word>standish</word><word>standoff</word><word>standoffish</word><word>standoffishness</word><word>standout</word><word>standpat</word><word>standpatism</word><word>standpatter</word><word>standpipe</word><word>standpoint</word><word>standpost</word><word>standstill</word></dict>