<dict><word>sizable</word><word>sizableness</word><word>sizably</word><word>sizal</word><word>sizar</word><word>sizarship</word><word>size</word><word>sized</word><word>sizeman</word><word>sizer</word><word>sizes</word><word>siziness</word><word>sizing</word><word>sizy</word><word>sizygia</word><word>sizygium</word><word>sizz</word><word>sizzard</word><word>sizzing</word><word>sizzle</word><word>sizzling</word><word>sizzlingly</word><word>sjambok</word><word>skaddle</word><word>skaff</word><word>skaffie</word><word>skag</word><word>skaillie</word><word>skainsmate</word><word>skair</word><word>skaitbird</word><word>skal</word><word>skalawag</word><word>skaldship</word><word>skance</word><word>skanda</word><word>skandhas</word><word>skart</word><word>skasely</word><word>skat</word><word>skat</word><word>skate</word><word>skateable</word><word>skater</word><word>skatikas</word><word>skatiku</word><word>skating</word><word>skatist</word><word>skatole</word><word>skatosine</word><word>skatoxyl</word><word>skaw</word><word>skean</word><word>skeanockle</word><word>skedaddle</word><word>skedaddler</word><word>skedge</word><word>skedgewith</word><word>skedlock</word><word>skee</word><word>skeed</word><word>skeeg</word><word>skeel</word><word>skeeling</word><word>skeely</word><word>skeen</word><word>skeenyie</word><word>skeer</word><word>skeered</word><word>skeery</word><word>skeesicks</word><word>skeet</word><word>skeeter</word><word>skeezix</word><word>skeg</word><word>skegger</word><word>skeif</word><word>skeigh</word><word>skeily</word><word>skein</word><word>skeiner</word><word>skeipp</word><word>skel</word><word>skelder</word><word>skelderdrake</word><word>skeldrake</word><word>skeletal</word><word>skeletin</word><word>skeletogenous</word><word>skeletogeny</word><word>skeletomuscular</word><word>skeleton</word><word>skeletonian</word><word>skeletonic</word><word>skeletonization</word><word>skeletonize</word><word>skeletonizer</word><word>skeletonless</word><word>skeletonweed</word><word>skeletony</word><word>skelf</word><word>skelgoose</word><word>skelic</word><word>skell</word><word>skellat</word><word>skeller</word><word>skelloch</word><word>skellum</word><word>skelly</word><word>skelp</word><word>skelper</word><word>skelpin</word><word>skelping</word><word>skelter</word><word>skeltonian</word><word>skeltonic</word><word>skeltonical</word><word>skeltonics</word><word>skemmel</word><word>skemp</word><word>sken</word><word>skene</word><word>skeo</word><word>skeough</word><word>skep</word><word>skepful</word><word>skeppist</word><word>skeppund</word><word>skeptic</word><word>skeptical</word><word>skeptically</word><word>skepticalness</word><word>skepticism</word><word>skepticize</word><word>sker</word><word>skere</word><word>skerret</word><word>skerrick</word><word>skerry</word><word>sketch</word><word>sketchability</word><word>sketchable</word><word>sketchbook</word><word>sketchee</word><word>sketcher</word><word>sketchily</word><word>sketchiness</word><word>sketching</word><word>sketchingly</word><word>sketchist</word><word>sketchlike</word><word>sketchy</word><word>skete</word><word>sketiotai</word><word>skeuomorph</word><word>skeuomorphic</word><word>skevish</word><word>skew</word><word>skewback</word><word>skewbacked</word><word>skewbald</word><word>skewed</word><word>skewer</word><word>skewerer</word><word>skewerwood</word><word>skewings</word><word>skewl</word><word>skewly</word><word>skewness</word><word>skewwhiff</word><word>skewwise</word><word>skewy</word><word>skey</word><word>skeyting</word><word>ski</word><word>skiagram</word><word>skiagraph</word><word>skiagrapher</word><word>skiagraphic</word><word>skiagraphical</word><word>skiagraphically</word><word>skiagraphy</word><word>skiameter</word><word>skiametry</word><word>skiapod</word><word>skiapodous</word><word>skiascope</word><word>skiascopy</word><word>skibby</word><word>skibslast</word><word>skice</word><word>skid</word><word>skidded</word><word>skidder</word><word>skidding</word><word>skiddingly</word><word>skiddoo</word><word>skiddy</word><word>skidi</word><word>skidpan</word><word>skidproof</word><word>skidway</word><word>skied</word><word>skieppe</word><word>skiepper</word><word>skier</word><word>skies</word><word>skiff</word><word>skiffless</word><word>skiffling</word><word>skift</word><word>skiing</word><word>skijore</word><word>skijorer</word><word>skijoring</word><word>skil</word><word>skilder</word><word>skildfel</word><word>skilfish</word><word>skill</word><word>skillagalee</word><word>skilled</word><word>skillenton</word><word>skillessness</word><word>skillet</word><word>skillful</word><word>skillfully</word><word>skillfulness</word><word>skilligalee</word><word>skilling</word><word>skillion</word><word>skilly</word><word>skilpot</word><word>skilts</word><word>skim</word><word>skimback</word><word>skime</word><word>skimmed</word><word>skimmer</word><word>skimmerton</word><word>skimmia</word><word>skimming</word><word>skimmingly</word><word>skimmington</word><word>skimmity</word><word>skimp</word><word>skimpily</word><word>skimpiness</word><word>skimpingly</word><word>skimpy</word></dict>