<dict><word>steeplechase</word><word>steeplechaser</word><word>steeplechasing</word><word>steepled</word><word>steepleless</word><word>steeplelike</word><word>steepletop</word><word>steeply</word><word>steepness</word><word>steepweed</word><word>steepwort</word><word>steepy</word><word>steer</word><word>steerability</word><word>steerable</word><word>steerage</word><word>steerageway</word><word>steerer</word><word>steering</word><word>steeringly</word><word>steerling</word><word>steerman</word><word>steermanship</word><word>steersman</word><word>steerswoman</word><word>steeve</word><word>steevely</word><word>steever</word><word>steeving</word><word>steg</word><word>steganogram</word><word>steganographical</word><word>steganographist</word><word>steganography</word><word>steganophthalmata</word><word>steganophthalmate</word><word>steganophthalmatous</word><word>steganophthalmia</word><word>steganopod</word><word>steganopodan</word><word>steganopodes</word><word>steganopodous</word><word>stegnosis</word><word>stegnotic</word><word>stegocarpous</word><word>stegocephalia</word><word>stegocephalian</word><word>stegocephalous</word><word>stegodon</word><word>stegodont</word><word>stegodontine</word><word>stegomus</word><word>stegomyia</word><word>stegosaur</word><word>stegosauria</word><word>stegosaurian</word><word>stegosauroid</word><word>stegosaurus</word><word>steid</word><word>steigh</word><word>stein</word><word>stein</word><word>steinberger</word><word>steinbok</word><word>steinerian</word><word>steinful</word><word>steinkirk</word><word>steironema</word><word>stekan</word><word>stela</word><word>stelae</word><word>stelai</word><word>stelar</word><word>stele</word><word>stell</word><word>stella</word><word>stella</word><word>stellar</word><word>stellaria</word><word>stellary</word><word>stellate</word><word>stellated</word><word>stellately</word><word>stellature</word><word>stelleridean</word><word>stellerine</word><word>stelliferous</word><word>stellification</word><word>stelliform</word><word>stellify</word><word>stelling</word><word>stellionate</word><word>stelliscript</word><word>stellite</word><word>stellite</word><word>stellular</word><word>stellularly</word><word>stellulate</word><word>stelography</word><word>stem</word><word>stema</word><word>stemhead</word><word>stemless</word><word>stemlet</word><word>stemlike</word><word>stemma</word><word>stemmata</word><word>stemmatiform</word><word>stemmatous</word><word>stemmed</word><word>stemmer</word><word>stemmery</word><word>stemming</word><word>stemmy</word><word>stemona</word><word>stemonaceae</word><word>stemonaceous</word><word>stemple</word><word>stempost</word><word>stemson</word><word>stemwards</word><word>stemware</word><word>sten</word><word>stenar</word><word>stench</word><word>stenchel</word><word>stenchful</word><word>stenching</word><word>stenchion</word><word>stenchy</word><word>stencil</word><word>stenciler</word><word>stencilmaker</word><word>stencilmaking</word><word>stend</word><word>steng</word><word>stengah</word><word>stenion</word><word>steno</word><word>stenobathic</word><word>stenobenthic</word><word>stenobragmatic</word><word>stenobregma</word><word>stenocardia</word><word>stenocardiac</word><word>stenocarpus</word><word>stenocephalia</word><word>stenocephalic</word><word>stenocephalous</word><word>stenocephaly</word><word>stenochoria</word><word>stenochrome</word><word>stenochromy</word><word>stenocoriasis</word><word>stenocranial</word><word>stenocrotaphia</word><word>stenofiber</word><word>stenog</word><word>stenogastric</word><word>stenogastry</word><word>stenoglossa</word><word>stenograph</word><word>stenographer</word><word>stenographic</word><word>stenographical</word><word>stenographically</word><word>stenographist</word><word>stenography</word><word>stenohaline</word><word>stenometer</word><word>stenopaic</word><word>stenopelmatidae</word><word>stenopetalous</word><word>stenophile</word><word>stenophragma</word><word>stenophyllous</word><word>stenorhyncous</word><word>stenosed</word><word>stenosepalous</word><word>stenosis</word><word>stenosphere</word><word>stenostomatous</word><word>stenostomia</word><word>stenotaphrum</word><word>stenotelegraphy</word><word>stenothermal</word><word>stenothorax</word><word>stenotic</word><word>stenotype</word><word>stenotypic</word><word>stenotypist</word><word>stenotypy</word><word>stent</word><word>stenter</word><word>stenterer</word><word>stenton</word><word>stentor</word><word>stentorian</word><word>stentorianly</word><word>stentorine</word><word>stentorious</word><word>stentoriously</word><word>stentoriousness</word><word>stentoronic</word><word>stentorophonic</word><word>stentrel</word><word>step</word><word>stepaunt</word><word>stepbairn</word><word>stepbrother</word><word>stepbrotherhood</word><word>stepchild</word><word>stepdame</word><word>stepdaughter</word><word>stepfather</word><word>stepfatherhood</word><word>stepfatherly</word><word>stepgrandchild</word><word>stepgrandfather</word><word>stepgrandmother</word><word>stepgrandson</word><word>stephana</word><word>stephane</word><word>stephanial</word><word>stephanian</word><word>stephanic</word><word>stephanion</word><word>stephanite</word><word>stephanoceros</word><word>stephanokontae</word><word>stephanome</word><word>stephanos</word><word>stephanotis</word><word>stephanotis</word><word>stephanurus</word><word>stephen</word><word>stepladder</word><word>stepless</word><word>steplike</word><word>stepminnie</word><word>stepmother</word><word>stepmotherhood</word><word>stepmotherless</word><word>stepmotherliness</word><word>stepmotherly</word><word>stepnephew</word><word>stepniece</word><word>stepparent</word><word>steppe</word><word>stepped</word></dict>